mesh_nav_3D/__init__.py
mesh_nav_3D/compare_planners.py
mesh_nav_3D/meshes/terrain_mesh.obj
mesh_nav_3D/outputs/plan_AStarPlanner_20250412_214037.json
mesh_nav_3D/outputs/plan_AStarPlanner_20250412_214037_points.npy
mesh_nav_3D/outputs/plan_HeatMethodPlanner_20250412_214037.json
mesh_nav_3D/outputs/plan_HeatMethodPlanner_20250412_214037_points.npy
mesh_nav_3D/planners/__init__.py
mesh_nav_3D/planners/a_star.py
mesh_nav_3D/planners/dijkstra.py
mesh_nav_3D/planners/edge_flip.py
mesh_nav_3D/planners/fmm.py
mesh_nav_3D/planners/greedy_bfs.py
mesh_nav_3D/planners/heat_method.py
mesh_nav_3D/planners/mmp.py
mesh_nav_3D/planners/mppi.py
mesh_nav_3D/planners/planner.py
mesh_nav_3D/planners/theta_star.py
mesh_nav_3D/visualize_planner.py
mesh_nav_3D/visualizer.py
mesh_nav_3d-0.1.0.dist-info/METADATA
mesh_nav_3d-0.1.0.dist-info/WHEEL
mesh_nav_3d-0.1.0.dist-info/RECORD
