Metadata-Version: 2.3
Name: mesh_nav_3D
Version: 0.1.0
Summary: 
License: MIT
Author: Otto Jerome
Author-email: o.jerome@ieee.org
Maintainer: Otto Jerome
Maintainer-email: o.jerome@ieee.org
Requires-Python: >=3.12,<4.0
Classifier: License :: OSI Approved :: MIT License
Classifier: Programming Language :: Python :: 3
Classifier: Programming Language :: Python :: 3.12
Classifier: Programming Language :: Python :: 3.13
Requires-Dist: potpourri3d (>=1.2.1,<2.0.0)
Requires-Dist: psutil (>=7.0.0,<8.0.0)
Requires-Dist: pydantic (>=2.11.2,<3.0.0)
Requires-Dist: pygeodesic (>=0.1.11,<0.2.0)
Requires-Dist: pyvista (>=0.44.2,<0.45.0)
Requires-Dist: tqdm (>=4.67.1,<5.0.0)
